swiftace/__init__.py
swiftace/cli.py
swiftace/utils/__init__.py
swiftace/utils/anaconda.py
swiftace/utils/api.py
swiftace/utils/authorization.py
swiftace/utils/checksum.py
swiftace/utils/credentials.py
swiftace/utils/data.py
swiftace/utils/git.py
swiftace/utils/jupyter.py
swiftace/utils/keras.py
swiftace-0.1.25.dist-info/DESCRIPTION.rst
swiftace-0.1.25.dist-info/METADATA
swiftace-0.1.25.dist-info/RECORD
swiftace-0.1.25.dist-info/WHEEL
swiftace-0.1.25.dist-info/entry_points.txt
swiftace-0.1.25.dist-info/metadata.json
swiftace-0.1.25.dist-info/top_level.txt
